setup.py
nectar/__init__.py
nectar/controller.py
nectar.egg-info/PKG-INFO
nectar.egg-info/SOURCES.txt
nectar.egg-info/dependency_links.txt
nectar.egg-info/requires.txt
nectar.egg-info/top_level.txt